{
"type": "FeatureCollection",
"name": "MCK UMUM",
"crs": { "type": "name", "properties": { "name": "urn:ogc:def:crs:OGC:1.3:CRS84" } },
"features": [
{ "type": "Feature", "id":  0, "properties": { "JENIS_SARANA": "MCK Umum", "KECAMATAN": "Banjarmasin Timur", "ALAMAT": "Jl. Manggis, Pasar Batuah", "KELURAHAN": "Kuripan" }, "geometry": { "type": "Point", "coordinates": [ 114.60971, -3.32026 ] } },
{ "type": "Feature", "id":  1, "properties": { "JENIS_SARANA": "MCK Umum", "KECAMATAN": "Banjarmasin Timur", "ALAMAT": "Jl. Manggis, Pasar Batuah", "KELURAHAN": "Kuripan" }, "geometry": { "type": "Point", "coordinates": [ 114.609408, -3.32026 ] } },
{ "type": "Feature", "id":  2, "properties": { "JENIS_SARANA": "MCK Umum", "KECAMATAN": "Banjarmasin Timur", "ALAMAT": "Jl. Manggis, Pasar Batuah", "KELURAHAN": "Kuripan" }, "geometry": { "type": "Point", "coordinates": [ 114.60906, -3.32025] } }
]
}
